pyperdeck/__init__.py
pyperdeck/_internals.py
pyperdeck/configuration.py
pyperdeck/timecode.py
pyperdeck-0.0.1.dist-info/LICENSE
pyperdeck-0.0.1.dist-info/METADATA
pyperdeck-0.0.1.dist-info/WHEEL
pyperdeck-0.0.1.dist-info/top_level.txt
pyperdeck-0.0.1.dist-info/RECORD
