Metadata-Version: 2.1
Name: pyperdeck
Version: 0.0.1
Summary: Python interface for Blackmagic Design HyperDeck recorders.
Home-page: https://github.com/FlantasticDan/pyperdeck
Author: Daniel Flanagan
License: UNKNOWN
Project-URL: Bug Tracker, https://github.com/FlantasticDan/pyperdeck/issues
Project-URL: Documentation, http://pyperdeck.readthedocs.io/
Platform: UNKNOWN
Classifier: Programming Language :: Python :: 3
Classifier: License :: OSI Approved :: MIT License
Classifier: Operating System :: OS Independent
Requires-Python: >=3.7
License-File: LICENSE
